{
  "kind": "collectionType",
  "collectionName": "user_documents",
  "info": {
    "singularName": "user-document",
    "pluralName": "user-documents",
    "displayName": "User Document",
    "description": ""
  },
  "options": {
    "draftAndPublish": true
  },
  "pluginOptions": {},
  "attributes": {
    "users_permissions_user": {
      "type": "relation",
      "relation": "oneToOne",
      "target": "plugin::users-permissions.user"
    },
    "companyName": {
      "type": "string"
    },
    "profilePicture": {
      "type": "media",
      "multiple": false,
      "required": false,
      "allowedTypes": [
        "images"
      ]
    },
    "templateType": {
      "type": "string"
    },
    "color": {
      "type": "string",
      "required": false,
      "default": "#0000"
    },
    "template": {
      "type": "component",
      "component": "template-components.template",
      "repeatable": false
    },
    "addProfilePicture": {
      "type": "boolean",
      "default": false,
      "required": false
    }
  }
}
